vllm_rbln/__init__.py
vllm_rbln/_version.py
vllm_rbln/forward_context.py
vllm_rbln/logger.py
vllm_rbln/platform.py
vllm_rbln/rbln_envs.py
vllm_rbln/attention/__init__.py
vllm_rbln/attention/layer.py
vllm_rbln/attention/backends/flash_attention.py
vllm_rbln/core/__init__.py
vllm_rbln/core/optimum_block_manager.py
vllm_rbln/core/optimum_scheduler.py
vllm_rbln/core/scheduler.py
vllm_rbln/core/block/__init__.py
vllm_rbln/core/block/optimum_block_table.py
vllm_rbln/distributed/rbln_communicator.py
vllm_rbln/lora/inputs.py
vllm_rbln/lora/layer.py
vllm_rbln/lora/mask.py
vllm_rbln/lora/punica_wrapper/punica_rbln.py
vllm_rbln/model_executor/__init__.py
vllm_rbln/model_executor/layers/__init__.py
vllm_rbln/model_executor/layers/logits_processor.py
vllm_rbln/model_executor/layers/vocab_parallel_embedding.py
vllm_rbln/model_executor/layers/fused_moe/__init__.py
vllm_rbln/model_executor/layers/fused_moe/layer.py
vllm_rbln/model_executor/layers/quantization/kernels/mixed_precision/__init__.py
vllm_rbln/model_executor/layers/quantization/kernels/mixed_precision/unpacked.py
vllm_rbln/model_executor/layers/rotary_embedding/base.py
vllm_rbln/model_executor/layers/rotary_embedding/deepseek_scaling_rope.py
vllm_rbln/model_executor/model_loader/__init__.py
vllm_rbln/model_executor/model_loader/rbln_model_loader.py
vllm_rbln/model_executor/model_loader/weight_loader.py
vllm_rbln/model_executor/models/optimum/__init__.py
vllm_rbln/model_executor/models/optimum/base.py
vllm_rbln/model_executor/models/optimum/blip2.py
vllm_rbln/model_executor/models/optimum/decoder_only.py
vllm_rbln/model_executor/models/optimum/encoder.py
vllm_rbln/model_executor/models/optimum/encoder_decoder.py
vllm_rbln/model_executor/models/optimum/gemma3.py
vllm_rbln/model_executor/models/optimum/idefics3.py
vllm_rbln/model_executor/models/optimum/llava.py
vllm_rbln/model_executor/models/optimum/llava_next.py
vllm_rbln/model_executor/models/optimum/model_base.py
vllm_rbln/model_executor/models/optimum/paligemma.py
vllm_rbln-0.10.0.dist-info/licenses/LICENSE
vllm_rbln-0.10.0.dist-info/METADATA
vllm_rbln-0.10.0.dist-info/WHEEL
vllm_rbln-0.10.0.dist-info/entry_points.txt
vllm_rbln-0.10.0.dist-info/top_level.txt
vllm_rbln-0.10.0.dist-info/RECORD
