Metadata-Version: 2.4
Name: vllm_rbln
Version: 0.10.0
Summary: vLLM plugin for RBLN NPU
Author-email: "Rebellions Inc." <support@rebellions.ai>
License:                                  Apache License
Project-URL: Homepage, https://rebellions.ai
Project-URL: Documentation, https://docs.rbln.ai
Project-URL: Repository, https://github.com/rbln-sw/vllm-rbln
Classifier: Programming Language :: Python :: 3.9
Classifier: Programming Language :: Python :: 3.10
Classifier: Programming Language :: Python :: 3.11
Classifier: Programming Language :: Python :: 3.12
Classifier: Programming Language :: Python :: 3.13
Classifier: Operating System :: POSIX :: Linux
Classifier: License :: OSI Approved :: Apache Software License
Classifier: Intended Audience :: Developers
Classifier: Intended Audience :: Information Technology
Classifier: Intended Audience :: Science/Research
Classifier: Topic :: Scientific/Engineering :: Artificial Intelligence
Classifier: Topic :: Scientific/Engineering :: Information Analysis
Requires-Python: >=3.9
License-File: LICENSE
Requires-Dist: setuptools>=64
Requires-Dist: setuptools-scm>=8
Requires-Dist: pyyaml
Requires-Dist: datasets
Requires-Dist: qwen_vl_utils
Requires-Dist: vllm==0.10.2
Requires-Dist: optimum-rbln>=0.10.0.post1
Requires-Dist: torch==2.8.0
Provides-Extra: test
Requires-Dist: pytest; extra == "test"
Requires-Dist: pytest-asyncio; extra == "test"
Requires-Dist: pytest-xdist; extra == "test"
Requires-Dist: pytest-cov; extra == "test"
Provides-Extra: build
Requires-Dist: build; extra == "build"
Requires-Dist: setuptools-scm; extra == "build"
Provides-Extra: dev
Requires-Dist: packaging; extra == "dev"
Requires-Dist: simphile; extra == "dev"
Requires-Dist: pynvml; extra == "dev"
Requires-Dist: huggingface_hub; extra == "dev"
Requires-Dist: fire; extra == "dev"
Dynamic: license-file
